chat/__init__.py
chat/admin.py
chat/apps.py
chat/consumers.py
chat/models.py
chat/routing.py
chat/tests.py
chat/urls.py
chat/views.py
chat/migrations/__init__.py
chat/templates/chat/index.html
chat/templates/chat/room.html
django_channels_chat-0.6.dist-info/LICENSE
django_channels_chat-0.6.dist-info/METADATA
django_channels_chat-0.6.dist-info/WHEEL
django_channels_chat-0.6.dist-info/top_level.txt
django_channels_chat-0.6.dist-info/RECORD
